web_server/__init__.py
web_server/merge_template.json
py_web_server_flask_Orinnass-1.2.3.dist-info/METADATA
py_web_server_flask_Orinnass-1.2.3.dist-info/WHEEL
py_web_server_flask_Orinnass-1.2.3.dist-info/top_level.txt
py_web_server_flask_Orinnass-1.2.3.dist-info/RECORD
